{"items":[{"key":"noob_note","value":"Note"},{"key":"noob_note_description","value":"Haha! What a noob!"},{"key":"blue_key","value":"Blue key"},{"key":"blue_key_description","value":"Key that can open blue door"},{"key":"magnetic_arm","value":"Magnetic Arm"},{"key":"magnetic_arm_description","value":"Allow to carry magnetic box"},{"key":"magnetic_boots","value":"Magnetic Boots"},{"key":"magnetic_boots_description","value":"Allow to walk on steel surface"},{"key":"red_key","value":"Red Key"},{"key":"red_key_description","value":"Allow to open boss door"},{"key":"add_to_inventory_message","value":"add to inventory"},{"key":"chest_info","value":"This chest is too rusty, can't open it"},{"key":"world_door","value":"Can't open this door by myself"},{"key":"blue_seal_door","value":"Blue magic seal on door"},{"key":"red_seal_door","value":"Red magic seal on door"},{"key":"blue_door","value":"Need a blue key to open the door"},{"key":"door_notification_key","value":"was removed from inventory"},{"key":"door_notification","value":"required"},{"key":"red_key_door","value":"You need red key to open the door"},{"key":"troll_note","value":"Note"},{"key":"troll_note_description","value":"What r u looking here soulja boy?"}]}